{
  "id": "2038117",
  "name": "yimutian",
  "font_family": "iconfont",
  "css_prefix_text": "icon-",
  "description": "",
  "glyphs": [
    {
      "icon_id": "14912957",
      "name": "亩",
      "font_class": "mu1",
      "unicode": "e604",
      "unicode_decimal": 58884
    },
    {
      "icon_id": "12410018",
      "name": "保障",
      "font_class": "baozhang",
      "unicode": "e600",
      "unicode_decimal": 58880
    },
    {
      "icon_id": "3234880",
      "name": "右箭头",
      "font_class": "youjiantou",
      "unicode": "e61f",
      "unicode_decimal": 58911
    },
    {
      "icon_id": "7085735",
      "name": "榜单-01",
      "font_class": "bangdan-",
      "unicode": "e759",
      "unicode_decimal": 59225
    },
    {
      "icon_id": "7547242",
      "name": "保",
      "font_class": "bao",
      "unicode": "e647",
      "unicode_decimal": 58951
    },
    {
      "icon_id": "1161616",
      "name": "眼睛",
      "font_class": "yanjing",
      "unicode": "e61c",
      "unicode_decimal": 58908
    },
    {
      "icon_id": "649143",
      "name": "购物车",
      "font_class": "gouwuche",
      "unicode": "e63b",
      "unicode_decimal": 58939
    },
    {
      "icon_id": "14444998",
      "name": "返回",
      "font_class": "fanhui",
      "unicode": "e72c",
      "unicode_decimal": 59180
    },
    {
      "icon_id": "16849363",
      "name": "更多3",
      "font_class": "gengduo3",
      "unicode": "e62b",
      "unicode_decimal": 58923
    },
    {
      "icon_id": "1236802",
      "name": "地图",
      "font_class": "weibiaoti-3",
      "unicode": "e603",
      "unicode_decimal": 58883
    },
    {
      "icon_id": "6006635",
      "name": "金牌-2",
      "font_class": "jinpai-",
      "unicode": "e68c",
      "unicode_decimal": 59020
    },
    {
      "icon_id": "11996850",
      "name": "同意",
      "font_class": "tongyi",
      "unicode": "e6f3",
      "unicode_decimal": 59123
    },
    {
      "icon_id": "12981526",
      "name": "企业",
      "font_class": "qiye",
      "unicode": "e64e",
      "unicode_decimal": 58958
    },
    {
      "icon_id": "14055582",
      "name": "微信",
      "font_class": "weixin",
      "unicode": "e61a",
      "unicode_decimal": 58906
    },
    {
      "icon_id": "551962",
      "name": "箭头",
      "font_class": "arrow-right",
      "unicode": "e602",
      "unicode_decimal": 58882
    },
    {
      "icon_id": "5640058",
      "name": "搜索",
      "font_class": "sousuo",
      "unicode": "e627",
      "unicode_decimal": 58919
    },
    {
      "icon_id": "693214",
      "name": "返回",
      "font_class": "flow",
      "unicode": "e612",
      "unicode_decimal": 58898
    },
    {
      "icon_id": "16589975",
      "name": "分享",
      "font_class": "59fenxiang",
      "unicode": "e632",
      "unicode_decimal": 58930
    },
    {
      "icon_id": "1268609",
      "name": "工厂",
      "font_class": "16",
      "unicode": "e62d",
      "unicode_decimal": 58925
    },
    {
      "icon_id": "3025173",
      "name": "化肥",
      "font_class": "huafei",
      "unicode": "e606",
      "unicode_decimal": 58886
    },
    {
      "icon_id": "5171794",
      "name": "酒",
      "font_class": "jiu",
      "unicode": "e614",
      "unicode_decimal": 58900
    },
    {
      "icon_id": "7795236",
      "name": "坚果",
      "font_class": "icon",
      "unicode": "e630",
      "unicode_decimal": 58928
    },
    {
      "icon_id": "7875682",
      "name": "茶叶",
      "font_class": "weibiaoti-",
      "unicode": "e601",
      "unicode_decimal": 58881
    },
    {
      "icon_id": "9281208",
      "name": "鸡蛋",
      "font_class": "jidan",
      "unicode": "e611",
      "unicode_decimal": 58897
    },
    {
      "icon_id": "9562330",
      "name": "人参",
      "font_class": "rencan",
      "unicode": "e624",
      "unicode_decimal": 58916
    },
    {
      "icon_id": "9720891",
      "name": "花椒",
      "font_class": "huajiao",
      "unicode": "e628",
      "unicode_decimal": 58920
    },
    {
      "icon_id": "12265972",
      "name": "粮油",
      "font_class": "liangyou",
      "unicode": "e631",
      "unicode_decimal": 58929
    },
    {
      "icon_id": "16277119",
      "name": "肉类",
      "font_class": "roulei",
      "unicode": "e617",
      "unicode_decimal": 58903
    },
    {
      "icon_id": "16452821",
      "name": "拖拉机@1x",
      "font_class": "tuolaji1x",
      "unicode": "e62f",
      "unicode_decimal": 58927
    }
  ]
}
